Metadata-Version: 2.1
Name: sinutils
Version: 0.0.3
Summary: A Python Utitlity Modules containing various useful functions.
Home-page: https://github.com/sintrb/sinutils/
Author: trb
Author-email: sintrb@gmail.com
License: UNKNOWN
Keywords: utils
Platform: UNKNOWN
